[
  {
    "timestamp": 1743192000,
    "open": 0.17852,
    "close": 0.18024,
    "high": 0.18156,
    "low": 0.17719,
    "volume": 9477216.8765
  },
  {
    "timestamp": 1743206400,
    "open": 0.18024,
    "close": 0.1787,
    "high": 0.18259,
    "low": 0.1751,
    "volume": 7882191.9359
  },
  {
    "timestamp": 1743220800,
    "open": 0.17858,
    "close": 0.17477,
    "high": 0.17975,
    "low": 0.17374,
    "volume": 12783229.0089
  },
  {
    "timestamp": 1743235200,
    "open": 0.17477,
    "close": 0.16989,
    "high": 0.17551,
    "low": 0.16842,
    "volume": 15399133.82327431
  },
  {
    "timestamp": 1743249600,
    "open": 0.16992,
    "close": 0.16981,
    "high": 0.17266,
    "low": 0.16949,
    "volume": 6735326.35713007
  },
  {
    "timestamp": 1743264000,
    "open": 0.16978,
    "close": 0.16932,
    "high": 0.17055,
    "low": 0.16585,
    "volume": 14733974.6247
  },
  {
    "timestamp": 1743278400,
    "open": 0.16924,
    "close": 0.16952,
    "high": 0.16983,
    "low": 0.16698,
    "volume": 6457839.50396705
  },
  {
    "timestamp": 1743292800,
    "open": 0.16958,
    "close": 0.17075,
    "high": 0.1724,
    "low": 0.16789,
    "volume": 7326279.05620612
  },
  {
    "timestamp": 1743307200,
    "open": 0.17073,
    "close": 0.17048,
    "high": 0.17218,
    "low": 0.1699,
    "volume": 4420311.91418589
  },
  {
    "timestamp": 1743321600,
    "open": 0.17045,
    "close": 0.16968,
    "high": 0.17208,
    "low": 0.16903,
    "volume": 5980335.26120094
  },
  {
    "timestamp": 1743336000,
    "open": 0.16974,
    "close": 0.16853,
    "high": 0.17092,
    "low": 0.16755,
    "volume": 6338726.4175
  },
  {
    "timestamp": 1743350400,
    "open": 0.16856,
    "close": 0.16934,
    "high": 0.17119,
    "low": 0.16612,
    "volume": 9200424.89934795
  },
  {
    "timestamp": 1743364800,
    "open": 0.16937,
    "close": 0.16648,
    "high": 0.16955,
    "low": 0.16447,
    "volume": 9130986.2944
  },
  {
    "timestamp": 1743379200,
    "open": 0.16652,
    "close": 0.16458,
    "high": 0.1681,
    "low": 0.16277,
    "volume": 9228101.9679
  },
  {
    "timestamp": 1743393600,
    "open": 0.16475,
    "close": 0.16342,
    "high": 0.16737,
    "low": 0.16227,
    "volume": 11355067.7353
  },
  {
    "timestamp": 1743408000,
    "open": 0.16343,
    "close": 0.16329,
    "high": 0.1649,
    "low": 0.16009,
    "volume": 14128615.1228
  },
  {
    "timestamp": 1743422400,
    "open": 0.16331,
    "close": 0.16706,
    "high": 0.16837,
    "low": 0.16081,
    "volume": 16019588.6221
  },
  {
    "timestamp": 1743436800,
    "open": 0.16705,
    "close": 0.16576,
    "high": 0.16815,
    "low": 0.16411,
    "volume": 21160014.61183043
  },
  {
    "timestamp": 1743451200,
    "open": 0.16572,
    "close": 0.16663,
    "high": 0.16696,
    "low": 0.16435,
    "volume": 8375875.3918
  },
  {
    "timestamp": 1743465600,
    "open": 0.16663,
    "close": 0.16847,
    "high": 0.16973,
    "low": 0.16602,
    "volume": 6485546.3299
  },
  {
    "timestamp": 1743480000,
    "open": 0.16864,
    "close": 0.16964,
    "high": 0.17093,
    "low": 0.16784,
    "volume": 6078209.5787
  },
  {
    "timestamp": 1743494400,
    "open": 0.16963,
    "close": 0.1705,
    "high": 0.17517,
    "low": 0.16962,
    "volume": 13460404.36559989
  },
  {
    "timestamp": 1743508800,
    "open": 0.1705,
    "close": 0.17493,
    "high": 0.17559,
    "low": 0.16726,
    "volume": 18719930.61385022
  },
  {
    "timestamp": 1743523200,
    "open": 0.17496,
    "close": 0.17215,
    "high": 0.17573,
    "low": 0.17114,
    "volume": 6863545.61000581
  },
  {
    "timestamp": 1743537600,
    "open": 0.17213,
    "close": 0.17398,
    "high": 0.17505,
    "low": 0.17102,
    "volume": 7029873.1626
  },
  {
    "timestamp": 1743552000,
    "open": 0.17399,
    "close": 0.17113,
    "high": 0.17404,
    "low": 0.16988,
    "volume": 12580276.9137
  },
  {
    "timestamp": 1743566400,
    "open": 0.1711,
    "close": 0.16972,
    "high": 0.17217,
    "low": 0.16776,
    "volume": 8441522.96352412
  },
  {
    "timestamp": 1743580800,
    "open": 0.16973,
    "close": 0.17126,
    "high": 0.17351,
    "low": 0.169,
    "volume": 7458960.7175
  },
  {
    "timestamp": 1743595200,
    "open": 0.17138,
    "close": 0.17617,
    "high": 0.17808,
    "low": 0.16943,
    "volume": 17462925.19871847
  },
  {
    "timestamp": 1743609600,
    "open": 0.17631,
    "close": 0.1743,
    "high": 0.17653,
    "low": 0.17058,
    "volume": 15632643.7399
  },
  {
    "timestamp": 1743624000,
    "open": 0.17431,
    "close": 0.16388,
    "high": 0.1801,
    "low": 0.16196,
    "volume": 33630270.81775885
  },
  {
    "timestamp": 1743638400,
    "open": 0.16378,
    "close": 0.16613,
    "high": 0.16673,
    "low": 0.16311,
    "volume": 8563038.9066
  },
  {
    "timestamp": 1743652800,
    "open": 0.16612,
    "close": 0.16436,
    "high": 0.16743,
    "low": 0.16343,
    "volume": 7668619.4138
  },
  {
    "timestamp": 1743667200,
    "open": 0.16428,
    "close": 0.16049,
    "high": 0.16504,
    "low": 0.15944,
    "volume": 10668885.43148555
  },
  {
    "timestamp": 1743681600,
    "open": 0.16039,
    "close": 0.15838,
    "high": 0.16106,
    "low": 0.15537,
    "volume": 25032072.7184
  },
  {
    "timestamp": 1743696000,
    "open": 0.15841,
    "close": 0.15866,
    "high": 0.15992,
    "low": 0.15709,
    "volume": 7119578.9852
  },
  {
    "timestamp": 1743710400,
    "open": 0.15871,
    "close": 0.1623,
    "high": 0.1623,
    "low": 0.15793,
    "volume": 6348923.7919
  },
  {
    "timestamp": 1743724800,
    "open": 0.16231,
    "close": 0.16265,
    "high": 0.16335,
    "low": 0.16002,
    "volume": 6911297.1367
  },
  {
    "timestamp": 1743739200,
    "open": 0.16265,
    "close": 0.16632,
    "high": 0.16685,
    "low": 0.16176,
    "volume": 8225940.3959
  },
  {
    "timestamp": 1743753600,
    "open": 0.16633,
    "close": 0.16231,
    "high": 0.16754,
    "low": 0.15997,
    "volume": 19631849.4321218
  },
  {
    "timestamp": 1743768000,
    "open": 0.16227,
    "close": 0.16755,
    "high": 0.17157,
    "low": 0.16159,
    "volume": 25351028.6201
  },
  {
    "timestamp": 1743782400,
    "open": 0.16754,
    "close": 0.16986,
    "high": 0.17207,
    "low": 0.16705,
    "volume": 9921495.8629
  },
  {
    "timestamp": 1743796800,
    "open": 0.16981,
    "close": 0.17126,
    "high": 0.17283,
    "low": 0.16864,
    "volume": 8510065.17796506
  },
  {
    "timestamp": 1743811200,
    "open": 0.17126,
    "close": 0.1694,
    "high": 0.17165,
    "low": 0.16931,
    "volume": 3658754.6977
  },
  {
    "timestamp": 1743825600,
    "open": 0.16939,
    "close": 0.16936,
    "high": 0.17004,
    "low": 0.16804,
    "volume": 5074591.9733
  },
  {
    "timestamp": 1743840000,
    "open": 0.16942,
    "close": 0.17012,
    "high": 0.1708,
    "low": 0.16861,
    "volume": 6588979.686
  },
  {
    "timestamp": 1743854400,
    "open": 0.17016,
    "close": 0.16725,
    "high": 0.17056,
    "low": 0.16609,
    "volume": 5572306.26486757
  },
  {
    "timestamp": 1743868800,
    "open": 0.16726,
    "close": 0.16755,
    "high": 0.16875,
    "low": 0.16695,
    "volume": 2860803.467
  },
  {
    "timestamp": 1743883200,
    "open": 0.16755,
    "close": 0.169,
    "high": 0.16931,
    "low": 0.16717,
    "volume": 3497341.4981
  },
  {
    "timestamp": 1743897600,
    "open": 0.16903,
    "close": 0.16767,
    "high": 0.17001,
    "low": 0.16715,
    "volume": 9480180.4073
  },
  {
    "timestamp": 1743912000,
    "open": 0.16768,
    "close": 0.16504,
    "high": 0.16796,
    "low": 0.16497,
    "volume": 7681472.7743
  },
  {
    "timestamp": 1743926400,
    "open": 0.16507,
    "close": 0.16429,
    "high": 0.16549,
    "low": 0.1636,
    "volume": 7292723.8792
  },
  {
    "timestamp": 1743940800,
    "open": 0.16427,
    "close": 0.16187,
    "high": 0.16456,
    "low": 0.1596,
    "volume": 11698987.80648812
  },
  {
    "timestamp": 1743955200,
    "open": 0.16171,
    "close": 0.15266,
    "high": 0.16171,
    "low": 0.15071,
    "volume": 35082652.5849
  },
  {
    "timestamp": 1743969600,
    "open": 0.15263,
    "close": 0.14928,
    "high": 0.15329,
    "low": 0.14583,
    "volume": 30928792.831
  },
  {
    "timestamp": 1743984000,
    "open": 0.1493,
    "close": 0.14208,
    "high": 0.15151,
    "low": 0.14022,
    "volume": 22308982.0416522
  },
  {
    "timestamp": 1743998400,
    "open": 0.14209,
    "close": 0.13227,
    "high": 0.14314,
    "low": 0.12971,
    "volume": 50898495.87356513
  },
  {
    "timestamp": 1744012800,
    "open": 0.13226,
    "close": 0.13816,
    "high": 0.1417,
    "low": 0.1318,
    "volume": 40369750.23818865
  },
  {
    "timestamp": 1744027200,
    "open": 0.13819,
    "close": 0.14706,
    "high": 0.15401,
    "low": 0.13724,
    "volume": 53926981.839
  },
  {
    "timestamp": 1744041600,
    "open": 0.14697,
    "close": 0.14667,
    "high": 0.14966,
    "low": 0.14387,
    "volume": 25250264.3486
  },
  {
    "timestamp": 1744056000,
    "open": 0.14668,
    "close": 0.14956,
    "high": 0.15239,
    "low": 0.14668,
    "volume": 18103257.73468904
  },
  {
    "timestamp": 1744070400,
    "open": 0.14953,
    "close": 0.15136,
    "high": 0.15332,
    "low": 0.14692,
    "volume": 17328036.4771
  },
  {
    "timestamp": 1744084800,
    "open": 0.15136,
    "close": 0.15079,
    "high": 0.15268,
    "low": 0.14839,
    "volume": 9122086.482
  },
  {
    "timestamp": 1744099200,
    "open": 0.15075,
    "close": 0.15605,
    "high": 0.15634,
    "low": 0.1497,
    "volume": 12937311.2586
  },
  {
    "timestamp": 1744113600,
    "open": 0.15629,
    "close": 0.15078,
    "high": 0.15703,
    "low": 0.15005,
    "volume": 27738100.9083743
  },
  {
    "timestamp": 1744128000,
    "open": 0.15078,
    "close": 0.14305,
    "high": 0.15111,
    "low": 0.142,
    "volume": 34889570.0659
  },
  {
    "timestamp": 1744142400,
    "open": 0.14305,
    "close": 0.14226,
    "high": 0.14472,
    "low": 0.14111,
    "volume": 10875803.4279
  },
  {
    "timestamp": 1744156800,
    "open": 0.14233,
    "close": 0.13885,
    "high": 0.1436,
    "low": 0.13653,
    "volume": 17316414.2471
  },
  {
    "timestamp": 1744171200,
    "open": 0.13874,
    "close": 0.14685,
    "high": 0.14759,
    "low": 0.1384,
    "volume": 23359170.7712
  },
  {
    "timestamp": 1744185600,
    "open": 0.14685,
    "close": 0.14385,
    "high": 0.1482,
    "low": 0.14311,
    "volume": 19539382.5802
  },
  {
    "timestamp": 1744200000,
    "open": 0.14383,
    "close": 0.14613,
    "high": 0.14917,
    "low": 0.143,
    "volume": 20302983.9915
  },
  {
    "timestamp": 1744214400,
    "open": 0.14615,
    "close": 0.1603,
    "high": 0.16208,
    "low": 0.14581,
    "volume": 44076579.51983428
  },
  {
    "timestamp": 1744228800,
    "open": 0.16031,
    "close": 0.16034,
    "high": 0.16422,
    "low": 0.16009,
    "volume": 11407589.886
  },
  {
    "timestamp": 1744243200,
    "open": 0.16028,
    "close": 0.15547,
    "high": 0.16049,
    "low": 0.15362,
    "volume": 15864127.65623558
  },
  {
    "timestamp": 1744257600,
    "open": 0.15546,
    "close": 0.15607,
    "high": 0.15835,
    "low": 0.15441,
    "volume": 12485356.1099
  },
  {
    "timestamp": 1744272000,
    "open": 0.1561,
    "close": 0.15629,
    "high": 0.15691,
    "low": 0.15492,
    "volume": 10099148.0567
  },
  {
    "timestamp": 1744286400,
    "open": 0.15628,
    "close": 0.1496,
    "high": 0.15857,
    "low": 0.1492,
    "volume": 24317742.9667
  },
  {
    "timestamp": 1744300800,
    "open": 0.14955,
    "close": 0.15379,
    "high": 0.15475,
    "low": 0.14885,
    "volume": 17571303.45085763
  },
  {
    "timestamp": 1744315200,
    "open": 0.15379,
    "close": 0.15357,
    "high": 0.15569,
    "low": 0.1531,
    "volume": 7499570.0174
  },
  {
    "timestamp": 1744329600,
    "open": 0.15356,
    "close": 0.15667,
    "high": 0.15753,
    "low": 0.15329,
    "volume": 8002996.63027395
  },
  {
    "timestamp": 1744344000,
    "open": 0.15683,
    "close": 0.15714,
    "high": 0.15823,
    "low": 0.15581,
    "volume": 5752633.71369389
  },
  {
    "timestamp": 1744358400,
    "open": 0.15716,
    "close": 0.158,
    "high": 0.16008,
    "low": 0.15621,
    "volume": 10488092.1612
  },
  {
    "timestamp": 1744372800,
    "open": 0.15805,
    "close": 0.15868,
    "high": 0.16004,
    "low": 0.1568,
    "volume": 13947569.31921149
  },
  {
    "timestamp": 1744387200,
    "open": 0.15872,
    "close": 0.15977,
    "high": 0.16107,
    "low": 0.15781,
    "volume": 7533668.8498
  },
  {
    "timestamp": 1744401600,
    "open": 0.15979,
    "close": 0.16006,
    "high": 0.16246,
    "low": 0.15947,
    "volume": 7460051.3487
  },
  {
    "timestamp": 1744416000,
    "open": 0.16011,
    "close": 0.15873,
    "high": 0.16023,
    "low": 0.15771,
    "volume": 6071340.2753
  },
  {
    "timestamp": 1744430400,
    "open": 0.15878,
    "close": 0.16286,
    "high": 0.1648,
    "low": 0.15852,
    "volume": 11343867.9227
  },
  {
    "timestamp": 1744444800,
    "open": 0.16297,
    "close": 0.16185,
    "high": 0.16426,
    "low": 0.16168,
    "volume": 6048425.73156301
  },
  {
    "timestamp": 1744459200,
    "open": 0.16185,
    "close": 0.16739,
    "high": 0.16871,
    "low": 0.16153,
    "volume": 16558083.0001
  },
  {
    "timestamp": 1744473600,
    "open": 0.16757,
    "close": 0.16635,
    "high": 0.16824,
    "low": 0.16485,
    "volume": 12457672.24406136
  },
  {
    "timestamp": 1744488000,
    "open": 0.16632,
    "close": 0.16756,
    "high": 0.16947,
    "low": 0.16626,
    "volume": 10506334.0424
  },
  {
    "timestamp": 1744502400,
    "open": 0.16767,
    "close": 0.16661,
    "high": 0.16865,
    "low": 0.16521,
    "volume": 6353904.7045
  },
  {
    "timestamp": 1744516800,
    "open": 0.16656,
    "close": 0.1641,
    "high": 0.16656,
    "low": 0.16391,
    "volume": 5630561.28399338
  },
  {
    "timestamp": 1744531200,
    "open": 0.16409,
    "close": 0.16512,
    "high": 0.16844,
    "low": 0.16348,
    "volume": 9531781.4084
  },
  {
    "timestamp": 1744545600,
    "open": 0.16516,
    "close": 0.16234,
    "high": 0.16565,
    "low": 0.16101,
    "volume": 8467241.8215
  },
  {
    "timestamp": 1744560000,
    "open": 0.16235,
    "close": 0.16296,
    "high": 0.16807,
    "low": 0.16103,
    "volume": 22868030.9827
  },
  {
    "timestamp": 1744574400,
    "open": 0.1629,
    "close": 0.16261,
    "high": 0.16556,
    "low": 0.16109,
    "volume": 14121522.4045
  },
  {
    "timestamp": 1744588800,
    "open": 0.16262,
    "close": 0.16544,
    "high": 0.16961,
    "low": 0.16223,
    "volume": 12269175.231
  },
  {
    "timestamp": 1744603200,
    "open": 0.16552,
    "close": 0.1644,
    "high": 0.16807,
    "low": 0.16272,
    "volume": 8396164.1181
  },
  {
    "timestamp": 1744617600,
    "open": 0.16447,
    "close": 0.16593,
    "high": 0.16628,
    "low": 0.16271,
    "volume": 12978488.4374
  },
  {
    "timestamp": 1744632000,
    "open": 0.16597,
    "close": 0.1603,
    "high": 0.16686,
    "low": 0.15945,
    "volume": 18810963.26489387
  },
  {
    "timestamp": 1744646400,
    "open": 0.16029,
    "close": 0.15984,
    "high": 0.16164,
    "low": 0.15909,
    "volume": 21268387.9227
  },
  {
    "timestamp": 1744660800,
    "open": 0.1599,
    "close": 0.15852,
    "high": 0.16005,
    "low": 0.15731,
    "volume": 5914258.0742
  },
  {
    "timestamp": 1744675200,
    "open": 0.15858,
    "close": 0.16086,
    "high": 0.16094,
    "low": 0.1574,
    "volume": 6520675.4704
  },
  {
    "timestamp": 1744689600,
    "open": 0.16086,
    "close": 0.15999,
    "high": 0.16119,
    "low": 0.15879,
    "volume": 4935899.2843
  },
  {
    "timestamp": 1744704000,
    "open": 0.15995,
    "close": 0.15873,
    "high": 0.16341,
    "low": 0.1562,
    "volume": 10028668.7844
  },
  {
    "timestamp": 1744718400,
    "open": 0.15866,
    "close": 0.15581,
    "high": 0.1613,
    "low": 0.1547,
    "volume": 24164934.6953
  },
  {
    "timestamp": 1744732800,
    "open": 0.15584,
    "close": 0.15498,
    "high": 0.15704,
    "low": 0.15445,
    "volume": 8687535.9586
  },
  {
    "timestamp": 1744747200,
    "open": 0.15502,
    "close": 0.15359,
    "high": 0.15626,
    "low": 0.15308,
    "volume": 11780115.1848
  },
  {
    "timestamp": 1744761600,
    "open": 0.15346,
    "close": 0.1551,
    "high": 0.15593,
    "low": 0.15216,
    "volume": 12133438.1147
  },
  {
    "timestamp": 1744776000,
    "open": 0.15504,
    "close": 0.1528,
    "high": 0.15552,
    "low": 0.15251,
    "volume": 7834705.11673692
  },
  {
    "timestamp": 1744790400,
    "open": 0.15283,
    "close": 0.15335,
    "high": 0.15432,
    "low": 0.15139,
    "volume": 7396388.2368
  },
  {
    "timestamp": 1744804800,
    "open": 0.15334,
    "close": 0.15513,
    "high": 0.15642,
    "low": 0.15192,
    "volume": 19342457.55073531
  },
  {
    "timestamp": 1744819200,
    "open": 0.15516,
    "close": 0.15565,
    "high": 0.15683,
    "low": 0.15024,
    "volume": 27584171.7779
  },
  {
    "timestamp": 1744833600,
    "open": 0.15563,
    "close": 0.15472,
    "high": 0.15742,
    "low": 0.15417,
    "volume": 13194669.60964871
  },
  {
    "timestamp": 1744848000,
    "open": 0.15468,
    "close": 0.15534,
    "high": 0.15706,
    "low": 0.15405,
    "volume": 14603567.0566
  },
  {
    "timestamp": 1744862400,
    "open": 0.15531,
    "close": 0.15669,
    "high": 0.15786,
    "low": 0.15493,
    "volume": 9853372.9402
  },
  {
    "timestamp": 1744876800,
    "open": 0.15675,
    "close": 0.15648,
    "high": 0.15712,
    "low": 0.15546,
    "volume": 5585045.1025
  },
  {
    "timestamp": 1744891200,
    "open": 0.15664,
    "close": 0.15527,
    "high": 0.15726,
    "low": 0.15301,
    "volume": 15520252.0529
  },
  {
    "timestamp": 1744905600,
    "open": 0.15524,
    "close": 0.15677,
    "high": 0.15943,
    "low": 0.15462,
    "volume": 21403621.4702
  },
  {
    "timestamp": 1744920000,
    "open": 0.15677,
    "close": 0.15576,
    "high": 0.15761,
    "low": 0.15525,
    "volume": 6738034.7384
  },
  {
    "timestamp": 1744934400,
    "open": 0.15588,
    "close": 0.15479,
    "high": 0.15609,
    "low": 0.15359,
    "volume": 8560565.0577
  },
  {
    "timestamp": 1744948800,
    "open": 0.1548,
    "close": 0.15513,
    "high": 0.15538,
    "low": 0.15419,
    "volume": 5802331.1118
  },
  {
    "timestamp": 1744963200,
    "open": 0.15516,
    "close": 0.15552,
    "high": 0.15619,
    "low": 0.15478,
    "volume": 9111026.1967
  },
  {
    "timestamp": 1744977600,
    "open": 0.15555,
    "close": 0.15637,
    "high": 0.15684,
    "low": 0.1552,
    "volume": 4871891.1524
  },
  {
    "timestamp": 1744992000,
    "open": 0.15635,
    "close": 0.15792,
    "high": 0.1588,
    "low": 0.15607,
    "volume": 9573218.8999
  },
  {
    "timestamp": 1745006400,
    "open": 0.15791,
    "close": 0.15761,
    "high": 0.15896,
    "low": 0.15739,
    "volume": 5452923.7324
  },
  {
    "timestamp": 1745020800,
    "open": 0.15761,
    "close": 0.15943,
    "high": 0.15969,
    "low": 0.15697,
    "volume": 7555016.9383
  },
  {
    "timestamp": 1745035200,
    "open": 0.15947,
    "close": 0.15905,
    "high": 0.16088,
    "low": 0.15832,
    "volume": 6549347.9401
  },
  {
    "timestamp": 1745049600,
    "open": 0.15906,
    "close": 0.15808,
    "high": 0.15926,
    "low": 0.15764,
    "volume": 5214334.7821
  },
  {
    "timestamp": 1745064000,
    "open": 0.15808,
    "close": 0.15785,
    "high": 0.15895,
    "low": 0.15737,
    "volume": 10368798.6273
  },
  {
    "timestamp": 1745078400,
    "open": 0.15781,
    "close": 0.15728,
    "high": 0.1584,
    "low": 0.15627,
    "volume": 5804441.43163608
  },
  {
    "timestamp": 1745092800,
    "open": 0.15733,
    "close": 0.15725,
    "high": 0.15814,
    "low": 0.15681,
    "volume": 5625549.0178
  },
  {
    "timestamp": 1745107200,
    "open": 0.1573,
    "close": 0.15835,
    "high": 0.15939,
    "low": 0.15709,
    "volume": 3493008.4096
  },
  {
    "timestamp": 1745121600,
    "open": 0.15836,
    "close": 0.15706,
    "high": 0.15955,
    "low": 0.15651,
    "volume": 5903539.0701
  },
  {
    "timestamp": 1745136000,
    "open": 0.15707,
    "close": 0.15335,
    "high": 0.15713,
    "low": 0.15275,
    "volume": 7886474.33406116
  },
  {
    "timestamp": 1745150400,
    "open": 0.15333,
    "close": 0.15287,
    "high": 0.15512,
    "low": 0.15236,
    "volume": 10652911.4815
  },
  {
    "timestamp": 1745164800,
    "open": 0.15286,
    "close": 0.15491,
    "high": 0.15499,
    "low": 0.15247,
    "volume": 7064767.7008
  },
  {
    "timestamp": 1745179200,
    "open": 0.15491,
    "close": 0.15529,
    "high": 0.15729,
    "low": 0.15348,
    "volume": 14863282.7312
  },
  {
    "timestamp": 1745193600,
    "open": 0.15534,
    "close": 0.16028,
    "high": 0.16139,
    "low": 0.15504,
    "volume": 20290302.8601
  },
  {
    "timestamp": 1745208000,
    "open": 0.16033,
    "close": 0.16194,
    "high": 0.1628,
    "low": 0.15963,
    "volume": 9648635.669
  },
  {
    "timestamp": 1745222400,
    "open": 0.16195,
    "close": 0.16152,
    "high": 0.16283,
    "low": 0.16022,
    "volume": 10330125.0227
  },
  {
    "timestamp": 1745236800,
    "open": 0.16153,
    "close": 0.16046,
    "high": 0.16357,
    "low": 0.15971,
    "volume": 17642150.2972
  },
  {
    "timestamp": 1745251200,
    "open": 0.16054,
    "close": 0.15858,
    "high": 0.16128,
    "low": 0.15583,
    "volume": 16676175.5616
  },
  {
    "timestamp": 1745265600,
    "open": 0.15846,
    "close": 0.15938,
    "high": 0.1595,
    "low": 0.15742,
    "volume": 3910329.2483
  },
  {
    "timestamp": 1745280000,
    "open": 0.15938,
    "close": 0.16095,
    "high": 0.16233,
    "low": 0.1572,
    "volume": 18704734.9381
  },
  {
    "timestamp": 1745294400,
    "open": 0.16102,
    "close": 0.16381,
    "high": 0.16476,
    "low": 0.16025,
    "volume": 9190111.8358
  },
  {
    "timestamp": 1745308800,
    "open": 0.1638,
    "close": 0.16408,
    "high": 0.16492,
    "low": 0.16288,
    "volume": 7739947.03645305
  },
  {
    "timestamp": 1745323200,
    "open": 0.16408,
    "close": 0.17194,
    "high": 0.17331,
    "low": 0.16377,
    "volume": 33028648.15583006
  },
  {
    "timestamp": 1745337600,
    "open": 0.17193,
    "close": 0.1718,
    "high": 0.17254,
    "low": 0.16998,
    "volume": 15081798.7764
  },
  {
    "timestamp": 1745352000,
    "open": 0.17175,
    "close": 0.17861,
    "high": 0.17995,
    "low": 0.17152,
    "volume": 22269384.6595
  },
  {
    "timestamp": 1745366400,
    "open": 0.17865,
    "close": 0.18216,
    "high": 0.1847,
    "low": 0.17865,
    "volume": 19679498.19970068
  },
  {
    "timestamp": 1745380800,
    "open": 0.18205,
    "close": 0.18217,
    "high": 0.18519,
    "low": 0.17997,
    "volume": 13828453.94039554
  },
  {
    "timestamp": 1745395200,
    "open": 0.18217,
    "close": 0.18225,
    "high": 0.18396,
    "low": 0.18067,
    "volume": 10237001.9425
  },
  {
    "timestamp": 1745409600,
    "open": 0.18227,
    "close": 0.17845,
    "high": 0.18543,
    "low": 0.1749,
    "volume": 31394584.5342
  },
  {
    "timestamp": 1745424000,
    "open": 0.17852,
    "close": 0.17837,
    "high": 0.18169,
    "low": 0.17661,
    "volume": 15880486.0647
  },
  {
    "timestamp": 1745438400,
    "open": 0.17834,
    "close": 0.17866,
    "high": 0.17992,
    "low": 0.17733,
    "volume": 7751117.2438
  },
  {
    "timestamp": 1745452800,
    "open": 0.17861,
    "close": 0.17301,
    "high": 0.17934,
    "low": 0.17281,
    "volume": 31231169.41
  },
  {
    "timestamp": 1745467200,
    "open": 0.17309,
    "close": 0.17244,
    "high": 0.17456,
    "low": 0.172,
    "volume": 16506496.74453316
  },
  {
    "timestamp": 1745481600,
    "open": 0.17249,
    "close": 0.1736,
    "high": 0.17412,
    "low": 0.16985,
    "volume": 14176238.70076535
  },
  {
    "timestamp": 1745496000,
    "open": 0.17362,
    "close": 0.17848,
    "high": 0.18077,
    "low": 0.17287,
    "volume": 22484371.2687
  },
  {
    "timestamp": 1745510400,
    "open": 0.1785,
    "close": 0.18095,
    "high": 0.18199,
    "low": 0.17761,
    "volume": 14982797.48178603
  },
  {
    "timestamp": 1745524800,
    "open": 0.181,
    "close": 0.18243,
    "high": 0.18327,
    "low": 0.1794,
    "volume": 15086555.4186
  },
  {
    "timestamp": 1745539200,
    "open": 0.1826,
    "close": 0.18041,
    "high": 0.18474,
    "low": 0.17752,
    "volume": 11847931.1628
  },
  {
    "timestamp": 1745553600,
    "open": 0.18046,
    "close": 0.1825,
    "high": 0.18298,
    "low": 0.17967,
    "volume": 13996057.9966
  },
  {
    "timestamp": 1745568000,
    "open": 0.18248,
    "close": 0.18284,
    "high": 0.18338,
    "low": 0.18023,
    "volume": 14648018.6103
  },
  {
    "timestamp": 1745582400,
    "open": 0.18301,
    "close": 0.18265,
    "high": 0.1862,
    "low": 0.17899,
    "volume": 30707410.291
  },
  {
    "timestamp": 1745596800,
    "open": 0.18271,
    "close": 0.18166,
    "high": 0.18485,
    "low": 0.18012,
    "volume": 25098470.1149
  },
  {
    "timestamp": 1745611200,
    "open": 0.18165,
    "close": 0.18158,
    "high": 0.18307,
    "low": 0.18016,
    "volume": 3134551.0406
  },
  {
    "timestamp": 1745625600,
    "open": 0.18162,
    "close": 0.18662,
    "high": 0.19294,
    "low": 0.18162,
    "volume": 28907991.2029
  },
  {
    "timestamp": 1745640000,
    "open": 0.18668,
    "close": 0.18597,
    "high": 0.18765,
    "low": 0.18371,
    "volume": 15240358.0610793
  },
  {
    "timestamp": 1745654400,
    "open": 0.18597,
    "close": 0.18155,
    "high": 0.18753,
    "low": 0.18095,
    "volume": 14354997.70407671
  },
  {
    "timestamp": 1745668800,
    "open": 0.18155,
    "close": 0.18246,
    "high": 0.18313,
    "low": 0.18022,
    "volume": 13296029.9288573
  },
  {
    "timestamp": 1745683200,
    "open": 0.18246,
    "close": 0.18121,
    "high": 0.1825,
    "low": 0.18037,
    "volume": 5214051.4018
  },
  {
    "timestamp": 1745697600,
    "open": 0.18115,
    "close": 0.18178,
    "high": 0.18236,
    "low": 0.18011,
    "volume": 9280544.43072538
  },
  {
    "timestamp": 1745712000,
    "open": 0.18196,
    "close": 0.17951,
    "high": 0.1835,
    "low": 0.17759,
    "volume": 22054452.3373
  },
  {
    "timestamp": 1745726400,
    "open": 0.17953,
    "close": 0.18022,
    "high": 0.18043,
    "low": 0.17654,
    "volume": 7845965.1352
  },
  {
    "timestamp": 1745740800,
    "open": 0.18022,
    "close": 0.18073,
    "high": 0.18256,
    "low": 0.17974,
    "volume": 6893990.3385
  },
  {
    "timestamp": 1745755200,
    "open": 0.18071,
    "close": 0.18009,
    "high": 0.18309,
    "low": 0.1792,
    "volume": 16808686.10160679
  },
  {
    "timestamp": 1745769600,
    "open": 0.18007,
    "close": 0.18227,
    "high": 0.18227,
    "low": 0.17768,
    "volume": 12646137.7344
  },
  {
    "timestamp": 1745784000,
    "open": 0.18228,
    "close": 0.17932,
    "high": 0.18238,
    "low": 0.17915,
    "volume": 7091180.8734
  },
  {
    "timestamp": 1745798400,
    "open": 0.17933,
    "close": 0.17878,
    "high": 0.17988,
    "low": 0.17381,
    "volume": 26160563.61558533
  },
  {
    "timestamp": 1745812800,
    "open": 0.1788,
    "close": 0.18123,
    "high": 0.18164,
    "low": 0.17871,
    "volume": 6789229.1032
  },
  {
    "timestamp": 1745827200,
    "open": 0.18127,
    "close": 0.18181,
    "high": 0.18274,
    "low": 0.17914,
    "volume": 10766891.99226916
  },
  {
    "timestamp": 1745841600,
    "open": 0.18188,
    "close": 0.17575,
    "high": 0.18188,
    "low": 0.17425,
    "volume": 13390651.5961
  },
  {
    "timestamp": 1745856000,
    "open": 0.17573,
    "close": 0.17888,
    "high": 0.17949,
    "low": 0.174,
    "volume": 12842984.7314
  },
  {
    "timestamp": 1745870400,
    "open": 0.17883,
    "close": 0.17899,
    "high": 0.17951,
    "low": 0.17743,
    "volume": 4158657.9247
  },
  {
    "timestamp": 1745884800,
    "open": 0.17911,
    "close": 0.1795,
    "high": 0.18071,
    "low": 0.177,
    "volume": 9353377.3937
  },
  {
    "timestamp": 1745899200,
    "open": 0.17943,
    "close": 0.1797,
    "high": 0.18059,
    "low": 0.17731,
    "volume": 7024450.4677
  },
  {
    "timestamp": 1745913600,
    "open": 0.17968,
    "close": 0.17907,
    "high": 0.18023,
    "low": 0.17772,
    "volume": 12014939.9236
  },
  {
    "timestamp": 1745928000,
    "open": 0.17915,
    "close": 0.17815,
    "high": 0.17992,
    "low": 0.1769,
    "volume": 8180445.2142
  },
  {
    "timestamp": 1745942400,
    "open": 0.17809,
    "close": 0.17852,
    "high": 0.18057,
    "low": 0.17775,
    "volume": 8858304.08171686
  },
  {
    "timestamp": 1745956800,
    "open": 0.17851,
    "close": 0.17473,
    "high": 0.17877,
    "low": 0.17244,
    "volume": 10854520.5201
  },
  {
    "timestamp": 1745971200,
    "open": 0.17461,
    "close": 0.17609,
    "high": 0.17663,
    "low": 0.17342,
    "volume": 5915043.0666
  },
  {
    "timestamp": 1745985600,
    "open": 0.17609,
    "close": 0.17345,
    "high": 0.1764,
    "low": 0.17258,
    "volume": 13232699.9966
  },
  {
    "timestamp": 1746000000,
    "open": 0.17345,
    "close": 0.17595,
    "high": 0.17612,
    "low": 0.17298,
    "volume": 9466582.0163
  },
  {
    "timestamp": 1746014400,
    "open": 0.17598,
    "close": 0.16977,
    "high": 0.17598,
    "low": 0.16677,
    "volume": 26798703.487
  },
  {
    "timestamp": 1746028800,
    "open": 0.16974,
    "close": 0.17224,
    "high": 0.1728,
    "low": 0.16883,
    "volume": 8635075.42495216
  },
  {
    "timestamp": 1746043200,
    "open": 0.17232,
    "close": 0.17224,
    "high": 0.17444,
    "low": 0.17199,
    "volume": 7479672.2977
  },
  {
    "timestamp": 1746057600,
    "open": 0.17224,
    "close": 0.17403,
    "high": 0.17546,
    "low": 0.17207,
    "volume": 9286792.667
  },
  {
    "timestamp": 1746072000,
    "open": 0.17415,
    "close": 0.17532,
    "high": 0.17556,
    "low": 0.17366,
    "volume": 3862975.6059
  },
  {
    "timestamp": 1746086400,
    "open": 0.1753,
    "close": 0.17933,
    "high": 0.17957,
    "low": 0.17502,
    "volume": 11153744.299
  },
  {
    "timestamp": 1746100800,
    "open": 0.17941,
    "close": 0.18062,
    "high": 0.1825,
    "low": 0.17686,
    "volume": 24331642.9387
  },
  {
    "timestamp": 1746115200,
    "open": 0.1807,
    "close": 0.1806,
    "high": 0.18333,
    "low": 0.18044,
    "volume": 13264039.43823301
  },
  {
    "timestamp": 1746129600,
    "open": 0.18062,
    "close": 0.18066,
    "high": 0.18239,
    "low": 0.18002,
    "volume": 8352858.8107
  },
  {
    "timestamp": 1746144000,
    "open": 0.18062,
    "close": 0.18244,
    "high": 0.18445,
    "low": 0.17981,
    "volume": 9601622.0545
  },
  {
    "timestamp": 1746158400,
    "open": 0.18245,
    "close": 0.17931,
    "high": 0.18291,
    "low": 0.17915,
    "volume": 7344011.83769177
  },
  {
    "timestamp": 1746172800,
    "open": 0.17933,
    "close": 0.18091,
    "high": 0.18165,
    "low": 0.17931,
    "volume": 4097973.6344
  },
  {
    "timestamp": 1746187200,
    "open": 0.18094,
    "close": 0.18145,
    "high": 0.1829,
    "low": 0.18006,
    "volume": 10128255.69790595
  },
  {
    "timestamp": 1746201600,
    "open": 0.18155,
    "close": 0.18011,
    "high": 0.18416,
    "low": 0.17958,
    "volume": 13988497.8045
  },
  {
    "timestamp": 1746216000,
    "open": 0.17998,
    "close": 0.18149,
    "high": 0.18242,
    "low": 0.17984,
    "volume": 5171203.4381924
  },
  {
    "timestamp": 1746230400,
    "open": 0.18151,
    "close": 0.18033,
    "high": 0.18219,
    "low": 0.18,
    "volume": 10906125.90639195
  },
  {
    "timestamp": 1746244800,
    "open": 0.18041,
    "close": 0.17893,
    "high": 0.18092,
    "low": 0.17832,
    "volume": 6348827.2178
  },
  {
    "timestamp": 1746259200,
    "open": 0.17895,
    "close": 0.1781,
    "high": 0.17967,
    "low": 0.17736,
    "volume": 5114056.474
  },
  {
    "timestamp": 1746273600,
    "open": 0.17811,
    "close": 0.17856,
    "high": 0.17954,
    "low": 0.17785,
    "volume": 9665145.43209946
  },
  {
    "timestamp": 1746288000,
    "open": 0.1785,
    "close": 0.17755,
    "high": 0.17855,
    "low": 0.1753,
    "volume": 5694654.2353
  },
  {
    "timestamp": 1746302400,
    "open": 0.17757,
    "close": 0.17568,
    "high": 0.17762,
    "low": 0.17525,
    "volume": 3732806.9693
  },
  {
    "timestamp": 1746316800,
    "open": 0.17565,
    "close": 0.17514,
    "high": 0.17738,
    "low": 0.1748,
    "volume": 6597495.447
  },
  {
    "timestamp": 1746331200,
    "open": 0.1752,
    "close": 0.17519,
    "high": 0.17652,
    "low": 0.17441,
    "volume": 4794833.8395
  },
  {
    "timestamp": 1746345600,
    "open": 0.17521,
    "close": 0.17407,
    "high": 0.1753,
    "low": 0.17337,
    "volume": 5288799.1208
  },
  {
    "timestamp": 1746360000,
    "open": 0.17411,
    "close": 0.17375,
    "high": 0.17477,
    "low": 0.17232,
    "volume": 9738448.46543753
  },
  {
    "timestamp": 1746374400,
    "open": 0.17373,
    "close": 0.17202,
    "high": 0.17399,
    "low": 0.17137,
    "volume": 12332854.21193176
  },
  {
    "timestamp": 1746388800,
    "open": 0.17207,
    "close": 0.17062,
    "high": 0.17307,
    "low": 0.16992,
    "volume": 18237533.9368
  },
  {
    "timestamp": 1746403200,
    "open": 0.17039,
    "close": 0.17039,
    "high": 0.17173,
    "low": 0.16839,
    "volume": 14063287.4481
  },
  {
    "timestamp": 1746417600,
    "open": 0.17037,
    "close": 0.17355,
    "high": 0.174,
    "low": 0.17026,
    "volume": 7794274.6502
  },
  {
    "timestamp": 1746432000,
    "open": 0.17358,
    "close": 0.17108,
    "high": 0.17462,
    "low": 0.1702,
    "volume": 9604347.9149
  },
  {
    "timestamp": 1746446400,
    "open": 0.17102,
    "close": 0.16894,
    "high": 0.17168,
    "low": 0.16852,
    "volume": 10469952.7792
  },
  {
    "timestamp": 1746460800,
    "open": 0.16893,
    "close": 0.17085,
    "high": 0.17257,
    "low": 0.16878,
    "volume": 7157608.7424
  },
  {
    "timestamp": 1746475200,
    "open": 0.17083,
    "close": 0.17056,
    "high": 0.17229,
    "low": 0.16827,
    "volume": 18675033.5963
  },
  {
    "timestamp": 1746489600,
    "open": 0.17067,
    "close": 0.16981,
    "high": 0.17114,
    "low": 0.16692,
    "volume": 8164416.8813
  },
  {
    "timestamp": 1746504000,
    "open": 0.16971,
    "close": 0.1694,
    "high": 0.17034,
    "low": 0.1688,
    "volume": 3280794.9251
  },
  {
    "timestamp": 1746518400,
    "open": 0.16935,
    "close": 0.1653,
    "high": 0.16935,
    "low": 0.1645,
    "volume": 10093578.3491
  },
  {
    "timestamp": 1746532800,
    "open": 0.16536,
    "close": 0.16656,
    "high": 0.16824,
    "low": 0.16426,
    "volume": 10469575.6268
  },
  {
    "timestamp": 1746547200,
    "open": 0.16669,
    "close": 0.16886,
    "high": 0.16978,
    "low": 0.16557,
    "volume": 6006806.9083
  },
  {
    "timestamp": 1746561600,
    "open": 0.16896,
    "close": 0.17218,
    "high": 0.17255,
    "low": 0.16718,
    "volume": 12121739.7602
  },
  {
    "timestamp": 1746576000,
    "open": 0.17227,
    "close": 0.1719,
    "high": 0.17441,
    "low": 0.17023,
    "volume": 13283704.0774
  },
  {
    "timestamp": 1746590400,
    "open": 0.17191,
    "close": 0.17331,
    "high": 0.17341,
    "low": 0.17153,
    "volume": 4250158.3448
  },
  {
    "timestamp": 1746604800,
    "open": 0.1733,
    "close": 0.17334,
    "high": 0.17399,
    "low": 0.1729,
    "volume": 3914042.1137
  },
  {
    "timestamp": 1746619200,
    "open": 0.17344,
    "close": 0.17088,
    "high": 0.17353,
    "low": 0.17055,
    "volume": 4399467.4861
  },
  {
    "timestamp": 1746633600,
    "open": 0.17084,
    "close": 0.16988,
    "high": 0.17268,
    "low": 0.16901,
    "volume": 22695951.3148
  },
  {
    "timestamp": 1746648000,
    "open": 0.1699,
    "close": 0.17204,
    "high": 0.17295,
    "low": 0.16923,
    "volume": 6317662.4808
  },
  {
    "timestamp": 1746662400,
    "open": 0.17214,
    "close": 0.17941,
    "high": 0.17954,
    "low": 0.17177,
    "volume": 18311961.4540357
  },
  {
    "timestamp": 1746676800,
    "open": 0.17946,
    "close": 0.18149,
    "high": 0.18275,
    "low": 0.17946,
    "volume": 18781700.8036
  },
  {
    "timestamp": 1746691200,
    "open": 0.18147,
    "close": 0.18306,
    "high": 0.18557,
    "low": 0.18143,
    "volume": 21912010.2938
  },
  {
    "timestamp": 1746705600,
    "open": 0.18319,
    "close": 0.18934,
    "high": 0.19135,
    "low": 0.1829,
    "volume": 20729645.3437
  },
  {
    "timestamp": 1746720000,
    "open": 0.18938,
    "close": 0.19092,
    "high": 0.19289,
    "low": 0.18924,
    "volume": 9998477.5771
  },
  {
    "timestamp": 1746734400,
    "open": 0.19097,
    "close": 0.19818,
    "high": 0.19841,
    "low": 0.18995,
    "volume": 21861149.2223
  },
  {
    "timestamp": 1746748800,
    "open": 0.19811,
    "close": 0.19351,
    "high": 0.19863,
    "low": 0.19321,
    "volume": 12972613.08
  },
  {
    "timestamp": 1746763200,
    "open": 0.19353,
    "close": 0.20589,
    "high": 0.2088,
    "low": 0.19295,
    "volume": 23343169.27584477
  },
  {
    "timestamp": 1746777600,
    "open": 0.20584,
    "close": 0.20728,
    "high": 0.21443,
    "low": 0.20185,
    "volume": 35957425.4565
  },
  {
    "timestamp": 1746792000,
    "open": 0.20724,
    "close": 0.20416,
    "high": 0.20994,
    "low": 0.20085,
    "volume": 24487550.735
  },
  {
    "timestamp": 1746806400,
    "open": 0.20431,
    "close": 0.20506,
    "high": 0.20618,
    "low": 0.2011,
    "volume": 13343662.9930202
  },
  {
    "timestamp": 1746820800,
    "open": 0.20514,
    "close": 0.2053,
    "high": 0.20608,
    "low": 0.20374,
    "volume": 9619188.27
  },
  {
    "timestamp": 1746835200,
    "open": 0.2052,
    "close": 0.20984,
    "high": 0.21083,
    "low": 0.20338,
    "volume": 13413192.6079
  },
  {
    "timestamp": 1746849600,
    "open": 0.20983,
    "close": 0.22404,
    "high": 0.2264,
    "low": 0.20827,
    "volume": 17034462.7325
  },
  {
    "timestamp": 1746864000,
    "open": 0.22427,
    "close": 0.2226,
    "high": 0.23082,
    "low": 0.22143,
    "volume": 20807166.86748766
  },
  {
    "timestamp": 1746878400,
    "open": 0.22268,
    "close": 0.22708,
    "high": 0.22915,
    "low": 0.22268,
    "volume": 16198308.3699342
  },
  {
    "timestamp": 1746892800,
    "open": 0.227,
    "close": 0.23529,
    "high": 0.23939,
    "low": 0.2264,
    "volume": 25871661.58525238
  },
  {
    "timestamp": 1746907200,
    "open": 0.23529,
    "close": 0.25067,
    "high": 0.25113,
    "low": 0.23224,
    "volume": 19518257.2527
  },
  {
    "timestamp": 1746921600,
    "open": 0.25065,
    "close": 0.23969,
    "high": 0.25978,
    "low": 0.23546,
    "volume": 52532094.12874894
  },
  {
    "timestamp": 1746936000,
    "open": 0.23963,
    "close": 0.23035,
    "high": 0.24259,
    "low": 0.22773,
    "volume": 25957712.852
  },
  {
    "timestamp": 1746950400,
    "open": 0.23028,
    "close": 0.23415,
    "high": 0.23481,
    "low": 0.22937,
    "volume": 19741082.965
  },
  {
    "timestamp": 1746964800,
    "open": 0.23419,
    "close": 0.22684,
    "high": 0.23632,
    "low": 0.22517,
    "volume": 30861412.1106
  },
  {
    "timestamp": 1746979200,
    "open": 0.22693,
    "close": 0.23102,
    "high": 0.23337,
    "low": 0.22213,
    "volume": 23415771.55071612
  },
  {
    "timestamp": 1746993600,
    "open": 0.23104,
    "close": 0.23183,
    "high": 0.23456,
    "low": 0.2292,
    "volume": 13598537.2707
  },
  {
    "timestamp": 1747008000,
    "open": 0.23187,
    "close": 0.23839,
    "high": 0.24131,
    "low": 0.23045,
    "volume": 33503731.0164
  },
  {
    "timestamp": 1747022400,
    "open": 0.23832,
    "close": 0.24396,
    "high": 0.25347,
    "low": 0.2363,
    "volume": 40623662.56426365
  },
  {
    "timestamp": 1747036800,
    "open": 0.24408,
    "close": 0.24224,
    "high": 0.25214,
    "low": 0.24055,
    "volume": 31131111.10577159
  },
  {
    "timestamp": 1747051200,
    "open": 0.24225,
    "close": 0.2324,
    "high": 0.24643,
    "low": 0.23068,
    "volume": 44834975.05011826
  },
  {
    "timestamp": 1747065600,
    "open": 0.23231,
    "close": 0.22732,
    "high": 0.23677,
    "low": 0.22048,
    "volume": 30880504.67887983
  },
  {
    "timestamp": 1747080000,
    "open": 0.22724,
    "close": 0.23102,
    "high": 0.2339,
    "low": 0.22544,
    "volume": 13686310.58295737
  },
  {
    "timestamp": 1747094400,
    "open": 0.23104,
    "close": 0.21847,
    "high": 0.23112,
    "low": 0.21736,
    "volume": 28041722.6343
  },
  {
    "timestamp": 1747108800,
    "open": 0.21843,
    "close": 0.22407,
    "high": 0.22583,
    "low": 0.21751,
    "volume": 17053365.38735632
  },
  {
    "timestamp": 1747123200,
    "open": 0.2241,
    "close": 0.22811,
    "high": 0.22995,
    "low": 0.223,
    "volume": 11397476.1597
  },
  {
    "timestamp": 1747137600,
    "open": 0.22814,
    "close": 0.23301,
    "high": 0.23353,
    "low": 0.2243,
    "volume": 24088965.6365
  },
  {
    "timestamp": 1747152000,
    "open": 0.23304,
    "close": 0.23902,
    "high": 0.24306,
    "low": 0.23291,
    "volume": 43059124.68654328
  },
  {
    "timestamp": 1747166400,
    "open": 0.23893,
    "close": 0.24081,
    "high": 0.24157,
    "low": 0.23661,
    "volume": 12741995.7802
  },
  {
    "timestamp": 1747180800,
    "open": 0.24097,
    "close": 0.23883,
    "high": 0.24339,
    "low": 0.23347,
    "volume": 19345484.6468418
  },
  {
    "timestamp": 1747195200,
    "open": 0.23886,
    "close": 0.23725,
    "high": 0.24754,
    "low": 0.23677,
    "volume": 17072646.0157
  },
  {
    "timestamp": 1747209600,
    "open": 0.23712,
    "close": 0.23745,
    "high": 0.23889,
    "low": 0.2319,
    "volume": 16731735.31377937
  },
  {
    "timestamp": 1747224000,
    "open": 0.23751,
    "close": 0.23298,
    "high": 0.23867,
    "low": 0.22964,
    "volume": 16332055.075
  },
  {
    "timestamp": 1747238400,
    "open": 0.23296,
    "close": 0.23428,
    "high": 0.23501,
    "low": 0.22814,
    "volume": 12706721.5098
  },
  {
    "timestamp": 1747252800,
    "open": 0.23425,
    "close": 0.23277,
    "high": 0.23515,
    "low": 0.23071,
    "volume": 5081837.705
  },
  {
    "timestamp": 1747267200,
    "open": 0.23281,
    "close": 0.23203,
    "high": 0.23677,
    "low": 0.22764,
    "volume": 11786136.66119125
  },
  {
    "timestamp": 1747281600,
    "open": 0.23201,
    "close": 0.22379,
    "high": 0.23499,
    "low": 0.22254,
    "volume": 21947053.1768
  },
  {
    "timestamp": 1747296000,
    "open": 0.22372,
    "close": 0.22673,
    "high": 0.22893,
    "low": 0.22204,
    "volume": 27845830.6676
  },
  {
    "timestamp": 1747310400,
    "open": 0.22672,
    "close": 0.22523,
    "high": 0.2294,
    "low": 0.21602,
    "volume": 28623059.5108
  },
  {
    "timestamp": 1747324800,
    "open": 0.22518,
    "close": 0.22199,
    "high": 0.22944,
    "low": 0.21891,
    "volume": 17744828.41608315
  },
  {
    "timestamp": 1747339200,
    "open": 0.22215,
    "close": 0.2194,
    "high": 0.22415,
    "low": 0.21371,
    "volume": 22162425.0054
  },
  {
    "timestamp": 1747353600,
    "open": 0.21939,
    "close": 0.22618,
    "high": 0.22724,
    "low": 0.21798,
    "volume": 15916394.6659
  },
  {
    "timestamp": 1747368000,
    "open": 0.22629,
    "close": 0.22579,
    "high": 0.22765,
    "low": 0.22377,
    "volume": 7702863.9146
  },
  {
    "timestamp": 1747382400,
    "open": 0.22579,
    "close": 0.22713,
    "high": 0.23005,
    "low": 0.22152,
    "volume": 12489370.1743
  },
  {
    "timestamp": 1747396800,
    "open": 0.22711,
    "close": 0.22897,
    "high": 0.22983,
    "low": 0.22463,
    "volume": 13935217.2307
  },
  {
    "timestamp": 1747411200,
    "open": 0.22896,
    "close": 0.22708,
    "high": 0.23093,
    "low": 0.22439,
    "volume": 11132397.2239
  },
  {
    "timestamp": 1747425600,
    "open": 0.22694,
    "close": 0.22114,
    "high": 0.22704,
    "low": 0.21969,
    "volume": 14212833.5542
  },
  {
    "timestamp": 1747440000,
    "open": 0.22106,
    "close": 0.21825,
    "high": 0.22223,
    "low": 0.21375,
    "volume": 17014861.9277
  },
  {
    "timestamp": 1747454400,
    "open": 0.21826,
    "close": 0.21711,
    "high": 0.22016,
    "low": 0.21593,
    "volume": 8288100.5118
  },
  {
    "timestamp": 1747468800,
    "open": 0.21713,
    "close": 0.21556,
    "high": 0.21737,
    "low": 0.21425,
    "volume": 9842613.6735
  },
  {
    "timestamp": 1747483200,
    "open": 0.21556,
    "close": 0.21507,
    "high": 0.21678,
    "low": 0.21173,
    "volume": 11600841.89740129
  },
  {
    "timestamp": 1747497600,
    "open": 0.21506,
    "close": 0.21456,
    "high": 0.21628,
    "low": 0.21079,
    "volume": 11024273.1253
  },
  {
    "timestamp": 1747512000,
    "open": 0.2145,
    "close": 0.21459,
    "high": 0.2178,
    "low": 0.21203,
    "volume": 9111697.3645
  },
  {
    "timestamp": 1747526400,
    "open": 0.21462,
    "close": 0.21568,
    "high": 0.21707,
    "low": 0.21404,
    "volume": 7528363.5053
  },
  {
    "timestamp": 1747540800,
    "open": 0.21568,
    "close": 0.22192,
    "high": 0.22211,
    "low": 0.21559,
    "volume": 8369056.74293112
  },
  {
    "timestamp": 1747555200,
    "open": 0.22189,
    "close": 0.22224,
    "high": 0.22518,
    "low": 0.22188,
    "volume": 8232894.9040253
  },
  {
    "timestamp": 1747569600,
    "open": 0.2222,
    "close": 0.23658,
    "high": 0.2375,
    "low": 0.22123,
    "volume": 15307192.5955
  },
  {
    "timestamp": 1747584000,
    "open": 0.23663,
    "close": 0.22251,
    "high": 0.23835,
    "low": 0.22195,
    "volume": 29241879.1563
  },
  {
    "timestamp": 1747598400,
    "open": 0.22229,
    "close": 0.23304,
    "high": 0.2345,
    "low": 0.2185,
    "volume": 15929478.28052822
  },
  {
    "timestamp": 1747612800,
    "open": 0.23317,
    "close": 0.21963,
    "high": 0.23578,
    "low": 0.21932,
    "volume": 16602794.9616635
  },
  {
    "timestamp": 1747627200,
    "open": 0.21956,
    "close": 0.21795,
    "high": 0.22148,
    "low": 0.21416,
    "volume": 16638298.70161156
  },
  {
    "timestamp": 1747641600,
    "open": 0.21789,
    "close": 0.2172,
    "high": 0.21812,
    "low": 0.21537,
    "volume": 7271939.2976
  },
  {
    "timestamp": 1747656000,
    "open": 0.21718,
    "close": 0.22124,
    "high": 0.22289,
    "low": 0.21384,
    "volume": 12811075.3166
  },
  {
    "timestamp": 1747670400,
    "open": 0.22121,
    "close": 0.22441,
    "high": 0.22615,
    "low": 0.21924,
    "volume": 17222228.81419356
  },
  {
    "timestamp": 1747684800,
    "open": 0.22447,
    "close": 0.22447,
    "high": 0.22543,
    "low": 0.22231,
    "volume": 12043044.3308
  },
  {
    "timestamp": 1747699200,
    "open": 0.22447,
    "close": 0.22575,
    "high": 0.23079,
    "low": 0.22365,
    "volume": 16272346.875
  },
  {
    "timestamp": 1747713600,
    "open": 0.22578,
    "close": 0.22235,
    "high": 0.22808,
    "low": 0.22187,
    "volume": 17233821.4553
  },
  {
    "timestamp": 1747728000,
    "open": 0.22242,
    "close": 0.22077,
    "high": 0.22331,
    "low": 0.21874,
    "volume": 13206635.1535
  },
  {
    "timestamp": 1747742400,
    "open": 0.22078,
    "close": 0.22058,
    "high": 0.22124,
    "low": 0.21766,
    "volume": 18075256.734
  },
  {
    "timestamp": 1747756800,
    "open": 0.22061,
    "close": 0.22424,
    "high": 0.22541,
    "low": 0.2178,
    "volume": 17945218.0405
  },
  {
    "timestamp": 1747771200,
    "open": 0.22416,
    "close": 0.22621,
    "high": 0.22784,
    "low": 0.22264,
    "volume": 18556162.87520273
  },
  {
    "timestamp": 1747785600,
    "open": 0.2263,
    "close": 0.22903,
    "high": 0.23055,
    "low": 0.224,
    "volume": 13653980.8452
  },
  {
    "timestamp": 1747800000,
    "open": 0.22906,
    "close": 0.2266,
    "high": 0.23355,
    "low": 0.22599,
    "volume": 21872356.4772
  },
  {
    "timestamp": 1747814400,
    "open": 0.22669,
    "close": 0.22652,
    "high": 0.22775,
    "low": 0.22471,
    "volume": 8025665.32652707
  },
  {
    "timestamp": 1747828800,
    "open": 0.22653,
    "close": 0.23189,
    "high": 0.23438,
    "low": 0.22547,
    "volume": 34560952.29650234
  },
  {
    "timestamp": 1747843200,
    "open": 0.23198,
    "close": 0.23018,
    "high": 0.23804,
    "low": 0.22272,
    "volume": 39536475.77
  },
  {
    "timestamp": 1747857600,
    "open": 0.23016,
    "close": 0.23403,
    "high": 0.23769,
    "low": 0.22793,
    "volume": 20333430.8692984
  },
  {
    "timestamp": 1747872000,
    "open": 0.23405,
    "close": 0.24111,
    "high": 0.24361,
    "low": 0.23387,
    "volume": 27939525.7286
  },
  {
    "timestamp": 1747886400,
    "open": 0.24123,
    "close": 0.24107,
    "high": 0.2425,
    "low": 0.23664,
    "volume": 14361573.4377
  },
  {
    "timestamp": 1747900800,
    "open": 0.24109,
    "close": 0.24032,
    "high": 0.24496,
    "low": 0.23902,
    "volume": 18320746.2795
  },
  {
    "timestamp": 1747915200,
    "open": 0.24037,
    "close": 0.24106,
    "high": 0.24285,
    "low": 0.2392,
    "volume": 17273183.3977
  },
  {
    "timestamp": 1747929600,
    "open": 0.2414,
    "close": 0.23933,
    "high": 0.24273,
    "low": 0.23828,
    "volume": 30231179.99
  },
  {
    "timestamp": 1747944000,
    "open": 0.23941,
    "close": 0.24559,
    "high": 0.24574,
    "low": 0.23768,
    "volume": 16619654.62060127
  },
  {
    "timestamp": 1747958400,
    "open": 0.24561,
    "close": 0.25106,
    "high": 0.25436,
    "low": 0.2436,
    "volume": 41848232.3083
  },
  {
    "timestamp": 1747972800,
    "open": 0.25114,
    "close": 0.24342,
    "high": 0.25152,
    "low": 0.24209,
    "volume": 17402288.725
  },
  {
    "timestamp": 1747987200,
    "open": 0.24345,
    "close": 0.23512,
    "high": 0.2489,
    "low": 0.23307,
    "volume": 14444533.7391
  },
  {
    "timestamp": 1748001600,
    "open": 0.23514,
    "close": 0.23436,
    "high": 0.23849,
    "low": 0.2272,
    "volume": 38460387.7339
  },
  {
    "timestamp": 1748016000,
    "open": 0.23455,
    "close": 0.23312,
    "high": 0.23692,
    "low": 0.23189,
    "volume": 14152475.3162
  },
  {
    "timestamp": 1748030400,
    "open": 0.23311,
    "close": 0.22511,
    "high": 0.23328,
    "low": 0.22302,
    "volume": 17573416.3457
  },
  {
    "timestamp": 1748044800,
    "open": 0.22509,
    "close": 0.22935,
    "high": 0.23005,
    "low": 0.22351,
    "volume": 12902099.1027
  },
  {
    "timestamp": 1748059200,
    "open": 0.22946,
    "close": 0.22733,
    "high": 0.2304,
    "low": 0.22675,
    "volume": 10983750.7684
  },
  {
    "timestamp": 1748073600,
    "open": 0.22734,
    "close": 0.22905,
    "high": 0.23037,
    "low": 0.22583,
    "volume": 12342323.9083
  },
  {
    "timestamp": 1748088000,
    "open": 0.22905,
    "close": 0.22773,
    "high": 0.22938,
    "low": 0.22685,
    "volume": 9637330.7556
  },
  {
    "timestamp": 1748102400,
    "open": 0.22773,
    "close": 0.22732,
    "high": 0.22896,
    "low": 0.22597,
    "volume": 5628431.2299
  },
  {
    "timestamp": 1748116800,
    "open": 0.22723,
    "close": 0.22507,
    "high": 0.2281,
    "low": 0.2238,
    "volume": 13795591.9146
  },
  {
    "timestamp": 1748131200,
    "open": 0.22501,
    "close": 0.2237,
    "high": 0.22642,
    "low": 0.21936,
    "volume": 14245239.9113
  },
  {
    "timestamp": 1748145600,
    "open": 0.22361,
    "close": 0.22134,
    "high": 0.22419,
    "low": 0.22051,
    "volume": 8391240.7895
  },
  {
    "timestamp": 1748160000,
    "open": 0.22138,
    "close": 0.21943,
    "high": 0.22138,
    "low": 0.21718,
    "volume": 13308288.9379
  },
  {
    "timestamp": 1748174400,
    "open": 0.21928,
    "close": 0.21851,
    "high": 0.22108,
    "low": 0.21569,
    "volume": 8008596.3402
  },
  {
    "timestamp": 1748188800,
    "open": 0.2185,
    "close": 0.22002,
    "high": 0.22081,
    "low": 0.21648,
    "volume": 8113822.6388
  },
  {
    "timestamp": 1748203200,
    "open": 0.22015,
    "close": 0.22492,
    "high": 0.22523,
    "low": 0.21833,
    "volume": 13716128.0353849
  },
  {
    "timestamp": 1748217600,
    "open": 0.22493,
    "close": 0.2272,
    "high": 0.2278,
    "low": 0.22339,
    "volume": 12709172.9455
  },
  {
    "timestamp": 1748232000,
    "open": 0.22724,
    "close": 0.22987,
    "high": 0.23038,
    "low": 0.22669,
    "volume": 8388662.8654
  },
  {
    "timestamp": 1748246400,
    "open": 0.22985,
    "close": 0.22619,
    "high": 0.23008,
    "low": 0.2253,
    "volume": 8046256.7646
  },
  {
    "timestamp": 1748260800,
    "open": 0.2262,
    "close": 0.22696,
    "high": 0.2287,
    "low": 0.22335,
    "volume": 12725029.3207
  },
  {
    "timestamp": 1748275200,
    "open": 0.22702,
    "close": 0.22429,
    "high": 0.22803,
    "low": 0.22252,
    "volume": 7251326.1187
  },
  {
    "timestamp": 1748289600,
    "open": 0.22409,
    "close": 0.226,
    "high": 0.22772,
    "low": 0.22338,
    "volume": 14749021.8971
  },
  {
    "timestamp": 1748304000,
    "open": 0.22604,
    "close": 0.2242,
    "high": 0.22708,
    "low": 0.21966,
    "volume": 11936652.6723
  },
  {
    "timestamp": 1748318400,
    "open": 0.22431,
    "close": 0.22765,
    "high": 0.22832,
    "low": 0.22249,
    "volume": 9238706.1265
  },
  {
    "timestamp": 1748332800,
    "open": 0.22775,
    "close": 0.22864,
    "high": 0.22909,
    "low": 0.22735,
    "volume": 8219614.5375452
  },
  {
    "timestamp": 1748347200,
    "open": 0.22864,
    "close": 0.22873,
    "high": 0.2321,
    "low": 0.22487,
    "volume": 18899692.0663
  },
  {
    "timestamp": 1748361600,
    "open": 0.2287,
    "close": 0.22702,
    "high": 0.23029,
    "low": 0.22661,
    "volume": 10993846.4375
  },
  {
    "timestamp": 1748376000,
    "open": 0.22727,
    "close": 0.22599,
    "high": 0.22868,
    "low": 0.22449,
    "volume": 10315257.4632
  },
  {
    "timestamp": 1748390400,
    "open": 0.22598,
    "close": 0.22478,
    "high": 0.22781,
    "low": 0.22302,
    "volume": 15406572.4982
  },
  {
    "timestamp": 1748404800,
    "open": 0.22472,
    "close": 0.22257,
    "high": 0.2253,
    "low": 0.22175,
    "volume": 9055695.7359
  },
  {
    "timestamp": 1748419200,
    "open": 0.22261,
    "close": 0.22357,
    "high": 0.22371,
    "low": 0.22091,
    "volume": 5378861.0357
  },
  {
    "timestamp": 1748433600,
    "open": 0.2236,
    "close": 0.21832,
    "high": 0.22469,
    "low": 0.21766,
    "volume": 10670584.46
  },
  {
    "timestamp": 1748448000,
    "open": 0.21838,
    "close": 0.21721,
    "high": 0.22113,
    "low": 0.21681,
    "volume": 5890543.5736
  },
  {
    "timestamp": 1748462400,
    "open": 0.21721,
    "close": 0.22095,
    "high": 0.22158,
    "low": 0.21702,
    "volume": 4091090.2929
  },
  {
    "timestamp": 1748476800,
    "open": 0.22081,
    "close": 0.22655,
    "high": 0.22795,
    "low": 0.21991,
    "volume": 12106947.5575
  },
  {
    "timestamp": 1748491200,
    "open": 0.22649,
    "close": 0.22415,
    "high": 0.22705,
    "low": 0.22219,
    "volume": 9406647.3703
  },
  {
    "timestamp": 1748505600,
    "open": 0.22437,
    "close": 0.22484,
    "high": 0.22604,
    "low": 0.22334,
    "volume": 4215329.85619863
  },
  {
    "timestamp": 1748520000,
    "open": 0.22487,
    "close": 0.21963,
    "high": 0.22487,
    "low": 0.218,
    "volume": 10157142.1629
  },
  {
    "timestamp": 1748534400,
    "open": 0.21964,
    "close": 0.21636,
    "high": 0.22146,
    "low": 0.21471,
    "volume": 23328250.301
  },
  {
    "timestamp": 1748548800,
    "open": 0.21635,
    "close": 0.2149,
    "high": 0.21952,
    "low": 0.21404,
    "volume": 9017385.1698
  },
  {
    "timestamp": 1748563200,
    "open": 0.21483,
    "close": 0.20853,
    "high": 0.21643,
    "low": 0.20066,
    "volume": 35261040.7933
  },
  {
    "timestamp": 1748577600,
    "open": 0.20847,
    "close": 0.20432,
    "high": 0.20951,
    "low": 0.20315,
    "volume": 13828456.1456
  },
  {
    "timestamp": 1748592000,
    "open": 0.20429,
    "close": 0.20508,
    "high": 0.20592,
    "low": 0.20152,
    "volume": 9435879.6842
  },
  {
    "timestamp": 1748606400,
    "open": 0.20505,
    "close": 0.20195,
    "high": 0.20583,
    "low": 0.20089,
    "volume": 12285106.71293742
  },
  {
    "timestamp": 1748620800,
    "open": 0.2021,
    "close": 0.20038,
    "high": 0.2028,
    "low": 0.19332,
    "volume": 21594916.5453
  },
  {
    "timestamp": 1748635200,
    "open": 0.20038,
    "close": 0.19361,
    "high": 0.2006,
    "low": 0.19059,
    "volume": 22631787.65
  },
  {
    "timestamp": 1748649600,
    "open": 0.19361,
    "close": 0.18924,
    "high": 0.19453,
    "low": 0.18552,
    "volume": 26545371.8382
  },
  {
    "timestamp": 1748664000,
    "open": 0.18931,
    "close": 0.1893,
    "high": 0.1911,
    "low": 0.1877,
    "volume": 13182956.685
  },
  {
    "timestamp": 1748678400,
    "open": 0.18929,
    "close": 0.18657,
    "high": 0.1897,
    "low": 0.18567,
    "volume": 14802365.9317
  },
  {
    "timestamp": 1748692800,
    "open": 0.18648,
    "close": 0.19179,
    "high": 0.19475,
    "low": 0.18632,
    "volume": 26764653.5167
  },
  {
    "timestamp": 1748707200,
    "open": 0.19174,
    "close": 0.19447,
    "high": 0.19504,
    "low": 0.19097,
    "volume": 6181204.1058
  },
  {
    "timestamp": 1748721600,
    "open": 0.19456,
    "close": 0.19252,
    "high": 0.19546,
    "low": 0.19219,
    "volume": 10727466.9955
  },
  {
    "timestamp": 1748736000,
    "open": 0.19258,
    "close": 0.19014,
    "high": 0.19258,
    "low": 0.1879,
    "volume": 11896796.163
  },
  {
    "timestamp": 1748750400,
    "open": 0.19011,
    "close": 0.19012,
    "high": 0.19217,
    "low": 0.18916,
    "volume": 5815214.0624
  },
  {
    "timestamp": 1748764800,
    "open": 0.19012,
    "close": 0.18942,
    "high": 0.19027,
    "low": 0.18645,
    "volume": 6659530.2486
  },
  {
    "timestamp": 1748779200,
    "open": 0.18941,
    "close": 0.19183,
    "high": 0.19248,
    "low": 0.18733,
    "volume": 8012257.74547461
  },
  {
    "timestamp": 1748793600,
    "open": 0.19183,
    "close": 0.19187,
    "high": 0.19466,
    "low": 0.18906,
    "volume": 15549202.42886029
  },
  {
    "timestamp": 1748808000,
    "open": 0.19188,
    "close": 0.19358,
    "high": 0.19512,
    "low": 0.19095,
    "volume": 8080816.1372
  },
  {
    "timestamp": 1748822400,
    "open": 0.19369,
    "close": 0.19027,
    "high": 0.19442,
    "low": 0.1892,
    "volume": 7721845.7853
  },
  {
    "timestamp": 1748836800,
    "open": 0.19028,
    "close": 0.19188,
    "high": 0.19338,
    "low": 0.18959,
    "volume": 5633821.3234744
  },
  {
    "timestamp": 1748851200,
    "open": 0.19185,
    "close": 0.18926,
    "high": 0.19308,
    "low": 0.1885,
    "volume": 11261066.34652675
  },
  {
    "timestamp": 1748865600,
    "open": 0.18918,
    "close": 0.19185,
    "high": 0.1931,
    "low": 0.1886,
    "volume": 12651649.96999548
  },
  {
    "timestamp": 1748880000,
    "open": 0.19192,
    "close": 0.19029,
    "high": 0.19372,
    "low": 0.18887,
    "volume": 7606904.9640038
  },
  {
    "timestamp": 1748894400,
    "open": 0.19029,
    "close": 0.19504,
    "high": 0.19642,
    "low": 0.19027,
    "volume": 9737893.77430135
  },
  {
    "timestamp": 1748908800,
    "open": 0.19501,
    "close": 0.19567,
    "high": 0.2005,
    "low": 0.19459,
    "volume": 20234803.87729016
  },
  {
    "timestamp": 1748923200,
    "open": 0.19572,
    "close": 0.19519,
    "high": 0.19649,
    "low": 0.19432,
    "volume": 5642455.9711
  },
  {
    "timestamp": 1748937600,
    "open": 0.19524,
    "close": 0.19516,
    "high": 0.19589,
    "low": 0.19332,
    "volume": 7464541.10320906
  },
  {
    "timestamp": 1748952000,
    "open": 0.19503,
    "close": 0.19735,
    "high": 0.19869,
    "low": 0.19405,
    "volume": 11941851.58660608
  },
  {
    "timestamp": 1748966400,
    "open": 0.19737,
    "close": 0.19713,
    "high": 0.19753,
    "low": 0.19516,
    "volume": 7670055.67489554
  },
  {
    "timestamp": 1748980800,
    "open": 0.19718,
    "close": 0.19309,
    "high": 0.19718,
    "low": 0.19138,
    "volume": 7815101.2264
  },
  {
    "timestamp": 1748995200,
    "open": 0.19304,
    "close": 0.19598,
    "high": 0.19704,
    "low": 0.19207,
    "volume": 5221545.59188706
  },
  {
    "timestamp": 1749009600,
    "open": 0.19604,
    "close": 0.1954,
    "high": 0.19664,
    "low": 0.19494,
    "volume": 4158519.2616
  },
  {
    "timestamp": 1749024000,
    "open": 0.19544,
    "close": 0.19367,
    "high": 0.19667,
    "low": 0.19365,
    "volume": 6511055.79462888
  },
  {
    "timestamp": 1749038400,
    "open": 0.1938,
    "close": 0.19285,
    "high": 0.19436,
    "low": 0.18964,
    "volume": 9170829.58155997
  },
  {
    "timestamp": 1749052800,
    "open": 0.1929,
    "close": 0.1893,
    "high": 0.1929,
    "low": 0.1893,
    "volume": 4486295.2893
  },
  {
    "timestamp": 1749067200,
    "open": 0.18928,
    "close": 0.18808,
    "high": 0.19024,
    "low": 0.18702,
    "volume": 11624587.3687
  },
  {
    "timestamp": 1749081600,
    "open": 0.18807,
    "close": 0.1901,
    "high": 0.19077,
    "low": 0.1874,
    "volume": 4989938.5051
  },
  {
    "timestamp": 1749096000,
    "open": 0.19017,
    "close": 0.18848,
    "high": 0.19074,
    "low": 0.18778,
    "volume": 7972250.7721
  },
  {
    "timestamp": 1749110400,
    "open": 0.18849,
    "close": 0.18939,
    "high": 0.18989,
    "low": 0.18779,
    "volume": 6826794.8998
  },
  {
    "timestamp": 1749124800,
    "open": 0.18937,
    "close": 0.18932,
    "high": 0.19246,
    "low": 0.18712,
    "volume": 15969026.4568
  },
  {
    "timestamp": 1749139200,
    "open": 0.18931,
    "close": 0.17379,
    "high": 0.18944,
    "low": 0.17066,
    "volume": 62419622.9048
  },
  {
    "timestamp": 1749153600,
    "open": 0.1739,
    "close": 0.17087,
    "high": 0.17445,
    "low": 0.16795,
    "volume": 58794538.7592936
  },
  {
    "timestamp": 1749168000,
    "open": 0.17103,
    "close": 0.1752,
    "high": 0.17545,
    "low": 0.16926,
    "volume": 15214134.5197
  },
  {
    "timestamp": 1749182400,
    "open": 0.17529,
    "close": 0.17478,
    "high": 0.17644,
    "low": 0.17437,
    "volume": 16659573.277
  },
  {
    "timestamp": 1749196800,
    "open": 0.1748,
    "close": 0.17763,
    "high": 0.17813,
    "low": 0.1748,
    "volume": 14395885.78432915
  },
  {
    "timestamp": 1749211200,
    "open": 0.17763,
    "close": 0.18184,
    "high": 0.18444,
    "low": 0.17738,
    "volume": 23326079.00517385
  },
  {
    "timestamp": 1749225600,
    "open": 0.1818,
    "close": 0.17898,
    "high": 0.18238,
    "low": 0.17843,
    "volume": 6799142.7816
  },
  {
    "timestamp": 1749240000,
    "open": 0.1791,
    "close": 0.17865,
    "high": 0.18059,
    "low": 0.17854,
    "volume": 5655981.8691
  },
  {
    "timestamp": 1749254400,
    "open": 0.17885,
    "close": 0.18256,
    "high": 0.18258,
    "low": 0.17778,
    "volume": 10083510.9166
  },
  {
    "timestamp": 1749268800,
    "open": 0.18258,
    "close": 0.18532,
    "high": 0.18638,
    "low": 0.18154,
    "volume": 9453645.3032
  },
  {
    "timestamp": 1749283200,
    "open": 0.18531,
    "close": 0.18602,
    "high": 0.18729,
    "low": 0.18442,
    "volume": 7812507.81733744
  },
  {
    "timestamp": 1749297600,
    "open": 0.18606,
    "close": 0.18671,
    "high": 0.18865,
    "low": 0.18577,
    "volume": 8592909.52981004
  },
  {
    "timestamp": 1749312000,
    "open": 0.18667,
    "close": 0.18325,
    "high": 0.18735,
    "low": 0.1819,
    "volume": 13998150.4769
  },
  {
    "timestamp": 1749326400,
    "open": 0.1833,
    "close": 0.18508,
    "high": 0.18639,
    "low": 0.18327,
    "volume": 4233223.8759
  },
  {
    "timestamp": 1749340800,
    "open": 0.18509,
    "close": 0.18327,
    "high": 0.18509,
    "low": 0.18316,
    "volume": 4096959.5139
  },
  {
    "timestamp": 1749355200,
    "open": 0.18332,
    "close": 0.18296,
    "high": 0.18483,
    "low": 0.18283,
    "volume": 3575528.9161
  },
  {
    "timestamp": 1749369600,
    "open": 0.18308,
    "close": 0.18374,
    "high": 0.18417,
    "low": 0.18045,
    "volume": 12213834.833
  },
  {
    "timestamp": 1749384000,
    "open": 0.18387,
    "close": 0.18415,
    "high": 0.18542,
    "low": 0.18246,
    "volume": 5142255.2037368
  },
  {
    "timestamp": 1749398400,
    "open": 0.18416,
    "close": 0.18613,
    "high": 0.18636,
    "low": 0.18394,
    "volume": 8667041.636
  },
  {
    "timestamp": 1749412800,
    "open": 0.18604,
    "close": 0.18416,
    "high": 0.18698,
    "low": 0.18367,
    "volume": 9619625.81660757
  },
  {
    "timestamp": 1749427200,
    "open": 0.18416,
    "close": 0.18262,
    "high": 0.18462,
    "low": 0.1812,
    "volume": 6012818.8263
  },
  {
    "timestamp": 1749441600,
    "open": 0.18265,
    "close": 0.1815,
    "high": 0.18282,
    "low": 0.17959,
    "volume": 10085245.1428
  },
  {
    "timestamp": 1749456000,
    "open": 0.18153,
    "close": 0.18636,
    "high": 0.18743,
    "low": 0.18085,
    "volume": 11036003.2625
  },
  {
    "timestamp": 1749470400,
    "open": 0.1864,
    "close": 0.18446,
    "high": 0.18658,
    "low": 0.18252,
    "volume": 14103114.82878398
  },
  {
    "timestamp": 1749484800,
    "open": 0.18459,
    "close": 0.18656,
    "high": 0.18793,
    "low": 0.18459,
    "volume": 16841784.4828
  },
  {
    "timestamp": 1749499200,
    "open": 0.18651,
    "close": 0.19483,
    "high": 0.19601,
    "low": 0.18651,
    "volume": 35058944.45317663
  },
  {
    "timestamp": 1749513600,
    "open": 0.19493,
    "close": 0.19362,
    "high": 0.1962,
    "low": 0.19285,
    "volume": 6664746.97908873
  },
  {
    "timestamp": 1749528000,
    "open": 0.19365,
    "close": 0.191,
    "high": 0.1939,
    "low": 0.18991,
    "volume": 8402826.29920478
  },
  {
    "timestamp": 1749542400,
    "open": 0.19103,
    "close": 0.19481,
    "high": 0.19593,
    "low": 0.18965,
    "volume": 14826147.6604
  },
  {
    "timestamp": 1749556800,
    "open": 0.19481,
    "close": 0.19111,
    "high": 0.19763,
    "low": 0.1888,
    "volume": 19094821.69956477
  },
  {
    "timestamp": 1749571200,
    "open": 0.19112,
    "close": 0.19463,
    "high": 0.19656,
    "low": 0.18999,
    "volume": 9257031.1726
  },
  {
    "timestamp": 1749585600,
    "open": 0.1946,
    "close": 0.19851,
    "high": 0.19855,
    "low": 0.19329,
    "volume": 12426093.2307
  },
  {
    "timestamp": 1749600000,
    "open": 0.19835,
    "close": 0.19765,
    "high": 0.19901,
    "low": 0.19467,
    "volume": 6906235.2091
  },
  {
    "timestamp": 1749614400,
    "open": 0.19762,
    "close": 0.20247,
    "high": 0.20666,
    "low": 0.1969,
    "volume": 16454116.671
  },
  {
    "timestamp": 1749628800,
    "open": 0.20246,
    "close": 0.19912,
    "high": 0.20387,
    "low": 0.19824,
    "volume": 12171938.3017
  },
  {
    "timestamp": 1749643200,
    "open": 0.19913,
    "close": 0.20318,
    "high": 0.2035,
    "low": 0.19832,
    "volume": 17178414.379
  },
  {
    "timestamp": 1749657600,
    "open": 0.20326,
    "close": 0.19503,
    "high": 0.20401,
    "low": 0.19415,
    "volume": 17101010.96605706
  },
  {
    "timestamp": 1749672000,
    "open": 0.19501,
    "close": 0.19297,
    "high": 0.19715,
    "low": 0.19131,
    "volume": 8778033.2406
  },
  {
    "timestamp": 1749686400,
    "open": 0.19291,
    "close": 0.19077,
    "high": 0.19366,
    "low": 0.19014,
    "volume": 6146971.3872
  },
  {
    "timestamp": 1749700800,
    "open": 0.19069,
    "close": 0.18956,
    "high": 0.1913,
    "low": 0.18904,
    "volume": 7916350.66461814
  },
  {
    "timestamp": 1749715200,
    "open": 0.1895,
    "close": 0.18713,
    "high": 0.19026,
    "low": 0.18643,
    "volume": 6544168.09704881
  },
  {
    "timestamp": 1749729600,
    "open": 0.18715,
    "close": 0.18585,
    "high": 0.18988,
    "low": 0.1856,
    "volume": 12825506.09893173
  },
  {
    "timestamp": 1749744000,
    "open": 0.18584,
    "close": 0.18482,
    "high": 0.19015,
    "low": 0.18379,
    "volume": 11156922.4433
  },
  {
    "timestamp": 1749758400,
    "open": 0.1847,
    "close": 0.18108,
    "high": 0.18564,
    "low": 0.17992,
    "volume": 19699017.6742
  },
  {
    "timestamp": 1749772800,
    "open": 0.18112,
    "close": 0.17439,
    "high": 0.18146,
    "low": 0.16987,
    "volume": 36613976.489
  },
  {
    "timestamp": 1749787200,
    "open": 0.17436,
    "close": 0.17437,
    "high": 0.17454,
    "low": 0.17153,
    "volume": 6534645.7326
  },
  {
    "timestamp": 1749801600,
    "open": 0.17439,
    "close": 0.1757,
    "high": 0.1764,
    "low": 0.17317,
    "volume": 9232663.44778924
  },
  {
    "timestamp": 1749816000,
    "open": 0.1757,
    "close": 0.17782,
    "high": 0.17873,
    "low": 0.17374,
    "volume": 11305472.2686
  },
  {
    "timestamp": 1749830400,
    "open": 0.17787,
    "close": 0.1765,
    "high": 0.17994,
    "low": 0.1756,
    "volume": 14199144.11158434
  },
  {
    "timestamp": 1749844800,
    "open": 0.17663,
    "close": 0.18041,
    "high": 0.18043,
    "low": 0.17611,
    "volume": 6768977.76069887
  },
  {
    "timestamp": 1749859200,
    "open": 0.1804,
    "close": 0.17781,
    "high": 0.1804,
    "low": 0.17703,
    "volume": 9828159.2296
  },
  {
    "timestamp": 1749873600,
    "open": 0.17779,
    "close": 0.17663,
    "high": 0.17849,
    "low": 0.17561,
    "volume": 6919661.25216362
  },
  {
    "timestamp": 1749888000,
    "open": 0.17661,
    "close": 0.17791,
    "high": 0.17797,
    "low": 0.17599,
    "volume": 4913448.1744
  },
  {
    "timestamp": 1749902400,
    "open": 0.17789,
    "close": 0.17674,
    "high": 0.17839,
    "low": 0.17572,
    "volume": 4455025.22098006
  },
  {
    "timestamp": 1749916800,
    "open": 0.17667,
    "close": 0.17606,
    "high": 0.17825,
    "low": 0.17458,
    "volume": 6617130.2759
  },
  {
    "timestamp": 1749931200,
    "open": 0.17613,
    "close": 0.17826,
    "high": 0.17854,
    "low": 0.17522,
    "volume": 3341186.7156
  },
  {
    "timestamp": 1749945600,
    "open": 0.17825,
    "close": 0.17763,
    "high": 0.17868,
    "low": 0.17733,
    "volume": 3180071.3322
  },
  {
    "timestamp": 1749960000,
    "open": 0.17767,
    "close": 0.17563,
    "high": 0.17842,
    "low": 0.17529,
    "volume": 7129128.2461
  },
  {
    "timestamp": 1749974400,
    "open": 0.17562,
    "close": 0.17421,
    "high": 0.17571,
    "low": 0.17362,
    "volume": 5429800.1503
  },
  {
    "timestamp": 1749988800,
    "open": 0.17425,
    "close": 0.17588,
    "high": 0.17739,
    "low": 0.17389,
    "volume": 8718879.7566
  },
  {
    "timestamp": 1750003200,
    "open": 0.17597,
    "close": 0.1736,
    "high": 0.17679,
    "low": 0.17271,
    "volume": 5441700.0529
  },
  {
    "timestamp": 1750017600,
    "open": 0.17363,
    "close": 0.17562,
    "high": 0.17594,
    "low": 0.17148,
    "volume": 10594394.1132
  },
  {
    "timestamp": 1750032000,
    "open": 0.17559,
    "close": 0.17594,
    "high": 0.17694,
    "low": 0.17283,
    "volume": 8534142.8363
  },
  {
    "timestamp": 1750046400,
    "open": 0.17592,
    "close": 0.17834,
    "high": 0.17885,
    "low": 0.17591,
    "volume": 6946791.1948
  },
  {
    "timestamp": 1750060800,
    "open": 0.17834,
    "close": 0.17676,
    "high": 0.17839,
    "low": 0.17539,
    "volume": 4438614.5988
  },
  {
    "timestamp": 1750075200,
    "open": 0.17674,
    "close": 0.17762,
    "high": 0.17944,
    "low": 0.17627,
    "volume": 6168802.7292
  },
  {
    "timestamp": 1750089600,
    "open": 0.17764,
    "close": 0.17992,
    "high": 0.18113,
    "low": 0.17727,
    "volume": 7068899.1311
  },
  {
    "timestamp": 1750104000,
    "open": 0.17993,
    "close": 0.17269,
    "high": 0.18033,
    "low": 0.17214,
    "volume": 16565923.44350194
  },
  {
    "timestamp": 1750118400,
    "open": 0.17269,
    "close": 0.17518,
    "high": 0.1761,
    "low": 0.16859,
    "volume": 20838311.8745
  },
  {
    "timestamp": 1750132800,
    "open": 0.1752,
    "close": 0.17376,
    "high": 0.17549,
    "low": 0.17309,
    "volume": 5318255.25111177
  },
  {
    "timestamp": 1750147200,
    "open": 0.1738,
    "close": 0.17138,
    "high": 0.17404,
    "low": 0.17058,
    "volume": 7167199.1434
  },
  {
    "timestamp": 1750161600,
    "open": 0.17135,
    "close": 0.16789,
    "high": 0.17235,
    "low": 0.16649,
    "volume": 14323208.4547
  },
  {
    "timestamp": 1750176000,
    "open": 0.16786,
    "close": 0.17037,
    "high": 0.17148,
    "low": 0.16394,
    "volume": 29850461.90770553
  },
  {
    "timestamp": 1750190400,
    "open": 0.17035,
    "close": 0.16933,
    "high": 0.17082,
    "low": 0.16835,
    "volume": 9794637.85844828
  },
  {
    "timestamp": 1750204800,
    "open": 0.16943,
    "close": 0.17065,
    "high": 0.17174,
    "low": 0.16911,
    "volume": 3210053.3097
  },
  {
    "timestamp": 1750219200,
    "open": 0.17072,
    "close": 0.17119,
    "high": 0.17223,
    "low": 0.17,
    "volume": 5091795.63646389
  },
  {
    "timestamp": 1750233600,
    "open": 0.17119,
    "close": 0.16869,
    "high": 0.17169,
    "low": 0.16624,
    "volume": 18643238.5423
  },
  {
    "timestamp": 1750248000,
    "open": 0.16862,
    "close": 0.16811,
    "high": 0.16946,
    "low": 0.16404,
    "volume": 17411704.4523
  },
  {
    "timestamp": 1750262400,
    "open": 0.16809,
    "close": 0.16697,
    "high": 0.16894,
    "low": 0.16522,
    "volume": 16404554.2625
  },
  {
    "timestamp": 1750276800,
    "open": 0.16709,
    "close": 0.17069,
    "high": 0.17157,
    "low": 0.16624,
    "volume": 7884556.0391
  },
  {
    "timestamp": 1750291200,
    "open": 0.17066,
    "close": 0.1709,
    "high": 0.17204,
    "low": 0.16935,
    "volume": 7037744.7496
  },
  {
    "timestamp": 1750305600,
    "open": 0.17097,
    "close": 0.17001,
    "high": 0.17152,
    "low": 0.16992,
    "volume": 16748197.4503
  },
  {
    "timestamp": 1750320000,
    "open": 0.16999,
    "close": 0.16901,
    "high": 0.17085,
    "low": 0.16854,
    "volume": 3096767.2196
  },
  {
    "timestamp": 1750334400,
    "open": 0.16899,
    "close": 0.16825,
    "high": 0.16997,
    "low": 0.16774,
    "volume": 5198479.8888
  },
  {
    "timestamp": 1750348800,
    "open": 0.16833,
    "close": 0.16978,
    "high": 0.17096,
    "low": 0.16803,
    "volume": 3400314.02902741
  },
  {
    "timestamp": 1750363200,
    "open": 0.16979,
    "close": 0.17092,
    "high": 0.17173,
    "low": 0.16926,
    "volume": 8841045.067
  },
  {
    "timestamp": 1750377600,
    "open": 0.17092,
    "close": 0.16933,
    "high": 0.17152,
    "low": 0.16915,
    "volume": 2486188.96
  },
  {
    "timestamp": 1750392000,
    "open": 0.16929,
    "close": 0.17054,
    "high": 0.1706,
    "low": 0.16712,
    "volume": 4664333.3776
  },
  {
    "timestamp": 1750406400,
    "open": 0.17055,
    "close": 0.17078,
    "high": 0.17139,
    "low": 0.16978,
    "volume": 3303746.4605
  },
  {
    "timestamp": 1750420800,
    "open": 0.17079,
    "close": 0.16599,
    "high": 0.17196,
    "low": 0.16555,
    "volume": 16838729.183
  },
  {
    "timestamp": 1750435200,
    "open": 0.16598,
    "close": 0.16287,
    "high": 0.16613,
    "low": 0.15837,
    "volume": 30389284.7538
  },
  {
    "timestamp": 1750449600,
    "open": 0.16281,
    "close": 0.16232,
    "high": 0.16431,
    "low": 0.161,
    "volume": 4070202.8052
  },
  {
    "timestamp": 1750464000,
    "open": 0.16231,
    "close": 0.16336,
    "high": 0.16379,
    "low": 0.162,
    "volume": 2586357.2065
  },
  {
    "timestamp": 1750478400,
    "open": 0.16336,
    "close": 0.16286,
    "high": 0.1635,
    "low": 0.16257,
    "volume": 4719484.3334
  },
  {
    "timestamp": 1750492800,
    "open": 0.16286,
    "close": 0.16324,
    "high": 0.16432,
    "low": 0.16272,
    "volume": 5566739.2152
  },
  {
    "timestamp": 1750507200,
    "open": 0.16333,
    "close": 0.16019,
    "high": 0.1635,
    "low": 0.15905,
    "volume": 7467084.10404149
  },
  {
    "timestamp": 1750521600,
    "open": 0.16022,
    "close": 0.15741,
    "high": 0.16095,
    "low": 0.15717,
    "volume": 9076585.4218
  },
  {
    "timestamp": 1750536000,
    "open": 0.15737,
    "close": 0.15444,
    "high": 0.15896,
    "low": 0.1501,
    "volume": 40538499.6326
  },
  {
    "timestamp": 1750550400,
    "open": 0.15451,
    "close": 0.15462,
    "high": 0.15771,
    "low": 0.15257,
    "volume": 21302976.32025933
  },
  {
    "timestamp": 1750564800,
    "open": 0.15464,
    "close": 0.15624,
    "high": 0.15729,
    "low": 0.15423,
    "volume": 8675382.7858
  },
  {
    "timestamp": 1750579200,
    "open": 0.1563,
    "close": 0.15548,
    "high": 0.15717,
    "low": 0.15357,
    "volume": 7870949.8184
  },
  {
    "timestamp": 1750593600,
    "open": 0.15553,
    "close": 0.14623,
    "high": 0.15636,
    "low": 0.14529,
    "volume": 49100322.5009
  },
  {
    "timestamp": 1750608000,
    "open": 0.14618,
    "close": 0.14737,
    "high": 0.15054,
    "low": 0.14562,
    "volume": 22766874.9821
  },
  {
    "timestamp": 1750622400,
    "open": 0.14745,
    "close": 0.15129,
    "high": 0.15178,
    "low": 0.14268,
    "volume": 30632181.1519
  },
  {
    "timestamp": 1750636800,
    "open": 0.15131,
    "close": 0.15215,
    "high": 0.15307,
    "low": 0.15065,
    "volume": 8631870.16008062
  },
  {
    "timestamp": 1750651200,
    "open": 0.15228,
    "close": 0.15388,
    "high": 0.15503,
    "low": 0.15195,
    "volume": 21871377.0913
  },
  {
    "timestamp": 1750665600,
    "open": 0.15387,
    "close": 0.15216,
    "high": 0.15455,
    "low": 0.1512,
    "volume": 6289165.849
  },
  {
    "timestamp": 1750680000,
    "open": 0.15219,
    "close": 0.15244,
    "high": 0.15658,
    "low": 0.15106,
    "volume": 26441108.9674
  },
  {
    "timestamp": 1750694400,
    "open": 0.15253,
    "close": 0.15721,
    "high": 0.15777,
    "low": 0.14861,
    "volume": 21048292.2601
  },
  {
    "timestamp": 1750708800,
    "open": 0.15732,
    "close": 0.16384,
    "high": 0.16525,
    "low": 0.15685,
    "volume": 23908050.1002
  },
  {
    "timestamp": 1750723200,
    "open": 0.16387,
    "close": 0.16293,
    "high": 0.16443,
    "low": 0.16189,
    "volume": 6046481.4865
  },
  {
    "timestamp": 1750737600,
    "open": 0.1629,
    "close": 0.16317,
    "high": 0.16767,
    "low": 0.16248,
    "volume": 11264906.5153
  },
  {
    "timestamp": 1750752000,
    "open": 0.16313,
    "close": 0.16358,
    "high": 0.16524,
    "low": 0.16226,
    "volume": 5659203.5215
  },
  {
    "timestamp": 1750766400,
    "open": 0.16362,
    "close": 0.16355,
    "high": 0.16479,
    "low": 0.16169,
    "volume": 7909159.7705
  },
  {
    "timestamp": 1750780800,
    "open": 0.16362,
    "close": 0.16374,
    "high": 0.16651,
    "low": 0.16272,
    "volume": 8673096.9531
  },
  {
    "timestamp": 1750795200,
    "open": 0.16365,
    "close": 0.16573,
    "high": 0.16576,
    "low": 0.16348,
    "volume": 5307258.3634
  },
  {
    "timestamp": 1750809600,
    "open": 0.16571,
    "close": 0.1654,
    "high": 0.16702,
    "low": 0.16454,
    "volume": 4338789.2142
  },
  {
    "timestamp": 1750824000,
    "open": 0.16542,
    "close": 0.1663,
    "high": 0.16745,
    "low": 0.1643,
    "volume": 3427347.422
  },
  {
    "timestamp": 1750838400,
    "open": 0.1663,
    "close": 0.16559,
    "high": 0.16655,
    "low": 0.16426,
    "volume": 3434996.8507
  },
  {
    "timestamp": 1750852800,
    "open": 0.1656,
    "close": 0.16298,
    "high": 0.16767,
    "low": 0.16256,
    "volume": 12787330.0862
  },
  {
    "timestamp": 1750867200,
    "open": 0.16297,
    "close": 0.16602,
    "high": 0.16652,
    "low": 0.16297,
    "volume": 9530713.7589
  },
  {
    "timestamp": 1750881600,
    "open": 0.16598,
    "close": 0.16457,
    "high": 0.1669,
    "low": 0.16353,
    "volume": 6278231.1757
  },
  {
    "timestamp": 1750896000,
    "open": 0.1646,
    "close": 0.1659,
    "high": 0.16809,
    "low": 0.16395,
    "volume": 7313364.6108
  },
  {
    "timestamp": 1750910400,
    "open": 0.16596,
    "close": 0.16495,
    "high": 0.16604,
    "low": 0.16387,
    "volume": 5962856.437
  },
  {
    "timestamp": 1750924800,
    "open": 0.16486,
    "close": 0.16165,
    "high": 0.16549,
    "low": 0.16112,
    "volume": 7225838.4384
  },
  {
    "timestamp": 1750939200,
    "open": 0.16159,
    "close": 0.16015,
    "high": 0.16186,
    "low": 0.15793,
    "volume": 18006595.4621
  },
  {
    "timestamp": 1750953600,
    "open": 0.16007,
    "close": 0.16032,
    "high": 0.16042,
    "low": 0.15921,
    "volume": 3033798.0629
  }
]